{
  "id": 38,
  "slug": "stream-takewhile-dropwhile",
  "title": "Stream takeWhile / dropWhile",
  "category": "streams",
  "difficulty": "beginner",
  "jdkVersion": "9",
  "oldLabel": "Java 8",
  "modernLabel": "Java 9+",
  "oldApproach": "Manual Loop",
  "modernApproach": "takeWhile/dropWhile",
  "oldCode": "List<Integer> result = new ArrayList<>();\nfor (int n : sorted) {\n    if (n >= 100) break;\n    result.add(n);\n}\n// no stream equivalent in Java 8",
  "modernCode": "var result = sorted.stream()\n    .takeWhile(n -> n < 100)\n    .toList();\n// or: .dropWhile(n -> n < 10)",
  "summary": "Take or drop elements from a stream based on a predicate.",
  "explanation": "takeWhile() returns elements while the predicate is true and stops at the first false. dropWhile() skips elements while true and returns the rest. Both work best on ordered streams.",
  "whyModernWins": [
    {
      "icon": "🎯",
      "title": "Short-circuit",
      "desc": "Stops processing as soon as the predicate fails."
    },
    {
      "icon": "🔗",
      "title": "Pipeline-friendly",
      "desc": "Chain with other stream operations naturally."
    },
    {
      "icon": "📖",
      "title": "Declarative",
      "desc": "takeWhile reads like English: 'take while less than 100'."
    }
  ],
  "support": "Widely available since JDK 9 (Sept 2017)",
  "prev": "streams/stream-iterate-predicate",
  "next": "streams/collectors-flatmapping",
  "related": [
    "streams/stream-tolist",
    "streams/stream-mapmulti",
    "streams/optional-or"
  ]
}
